noun_verb/__init__.py
noun_verb/main.py
noun_verb/prompts.py
noun_verb-2025.12.21234620.dist-info/METADATA
noun_verb-2025.12.21234620.dist-info/WHEEL
noun_verb-2025.12.21234620.dist-info/top_level.txt
noun_verb-2025.12.21234620.dist-info/RECORD
