Metadata-Version: 2.4
Name: noun-verb
Version: 2025.12.21234620
Summary: noun-verb is a package that reframes self-concept from fixed labels (nouns) to dynamic actions (verbs).
Author-email: noun-verb <hi@eugene.plus>
License: MIT
Project-URL: Homepage, https://github.com/chigwell/noun-verb
Requires-Python: >=3.9
Requires-Dist: langchain-llm7>=0.0.0
Requires-Dist: llmatch-messages>=0.0.0
Requires-Dist: langchain-core>=0.3.0
